okcourse/__init__.py
okcourse/constants.py
okcourse/models.py
okcourse/prompt_library.py
okcourse/py.typed
okcourse/generators/__init__.py
okcourse/generators/base.py
okcourse/generators/openai/__init__.py
okcourse/generators/openai/async_openai.py
okcourse/generators/openai/openai_utils.py
okcourse/utils/__init__.py
okcourse/utils/audio_utils.py
okcourse/utils/log_utils.py
okcourse/utils/misc_utils.py
okcourse/utils/text_utils.py
okcourse-0.1.13.dist-info/METADATA
okcourse-0.1.13.dist-info/WHEEL
okcourse-0.1.13.dist-info/licenses/LICENSE
okcourse-0.1.13.dist-info/RECORD
