Metadata-Version: 2.4
Name: okcourse
Version: 0.1.13
Summary: Generate audiobook-style courses with lectures on any topic using Python and AI.
Project-URL: Homepage, https://github.com/mmacy/okcourse/
Project-URL: Documentation, https://mmacy.github.io/okcourse
Project-URL: Repository, https://github.com/mmacy/okcourse/
Author-email: Marsh Macy <mmacy@users.noreply.github.com>
License: CC0 1.0 Universal
License-File: LICENSE
Requires-Python: >=3.12
Requires-Dist: mutagen>=1.47.0
Requires-Dist: nltk>=3.9.1
Requires-Dist: openai>=1.61.0
